mutalyzer_mutator/__init__.py
mutalyzer_mutator/mutator.py
mutalyzer_mutator/util.py
mutalyzer_mutator-0.2.0.dist-info/LICENSE
mutalyzer_mutator-0.2.0.dist-info/METADATA
mutalyzer_mutator-0.2.0.dist-info/WHEEL
mutalyzer_mutator-0.2.0.dist-info/top_level.txt
mutalyzer_mutator-0.2.0.dist-info/RECORD
