Metadata-Version: 2.1
Name: mutalyzer-mutator
Version: 0.2.0
Summary: Mutalyzer sequence mutator.
Home-page: http://github.com/mutalyzer/mutator
Author: Mihai Lefter
Author-email: M.Lefter@lumc.nl
License: MIT
Keywords: Mutalyzer,mutate,description,sequence,dna,variant
Platform: UNKNOWN
License-File: LICENSE
Provides-Extra: test
Requires-Dist: pytest (==6.2.4) ; extra == 'test'
